hello_juan
