Metadata-Version: 1.1
Name: hello-juan
Version: 0.3
Summary: Un saludo a Juan
Home-page: https://github.com/juanmosca/hello_juan.git
Author: Juan Manuel Mosca
Author-email: juanmosca@gmail.com
License: UNKNOWN
Download-URL: https://github.com/juanmosca/hello_juan/archive/0.2.tar.gz
Keywords: testing,logging,example
Platform: UNKNOWN
